microchain/__main__.py
microchain/firmware.py
microchain/mcu.py
microchain/project.py
microchain-0.0.4.dist-info/LICENSE
microchain-0.0.4.dist-info/METADATA
microchain-0.0.4.dist-info/WHEEL
microchain-0.0.4.dist-info/top_level.txt
microchain-0.0.4.dist-info/RECORD
