Metadata-Version: 2.1
Name: microchain
Version: 0.0.4
Summary: Toolchain for micropython and microcontrollers
Home-page: https://github.com/damiencorpataux/microchain
Author: Damien Corpataux
Author-email: d@mien.ch
License: UNKNOWN
Platform: UNKNOWN
Classifier: Programming Language :: Python :: 3
Requires-Python: >=3.6
Requires-Dist: esptool
Requires-Dist: rshell
Requires-Dist: adafruit-ampy
Requires-Dist: pyserial
Requires-Dist: sh
Requires-Dist: requests
Requires-Dist: click
Requires-Dist: rich
